LICENSE
README.md
setup.py
abp/__init__.py
abp/decode.py
abp/encode.py
abp/k2p.py
abp_tools.egg-info/PKG-INFO
abp_tools.egg-info/SOURCES.txt
abp_tools.egg-info/dependency_links.txt
abp_tools.egg-info/top_level.txt