Metadata-Version: 2.1
Name: abp-tools
Version: 0.1.1
Summary: ABP is an encryption algorithm.
Home-page: https://github.com/Geniusum/abp
Author: Genius_um
License: UNKNOWN
Platform: UNKNOWN
Classifier: Programming Language :: Python :: 3
Classifier: Operating System :: OS Independent
Requires-Python: >=3.9
License-File: LICENSE
